[
  {
    "full_name": "dicebear/dicebear",
    "stargazers_count": 8433,
    "open_issues_count": 0,
    "forks_count": 365
  },
  {
    "full_name": "ultraworkers/claw-code",
    "stargazers_count": 183575,
    "open_issues_count": 1413,
    "forks_count": 107902
  },
  {
    "full_name": "FranciscoMoretti/chat-js",
    "stargazers_count": 1169,
    "open_issues_count": 21,
    "forks_count": 108
  },
  {
    "full_name": "allipiopereira/turborepo-bun-next-expo",
    "stargazers_count": 128,
    "open_issues_count": 1,
    "forks_count": 17
  },
  {
    "full_name": "jnsahaj/tweakcn",
    "stargazers_count": 9676,
    "open_issues_count": 53,
    "forks_count": 618
  },
  {
    "full_name": "rybbit-io/rybbit",
    "stargazers_count": 11983,
    "open_issues_count": 161,
    "forks_count": 637
  },
  {
    "full_name": "vercel/next-forge",
    "stargazers_count": 7024,
    "open_issues_count": 17,
    "forks_count": 645
  },
  {
    "full_name": "HumeAI/hume-evi-next-js-starter",
    "stargazers_count": 662,
    "open_issues_count": 0,
    "forks_count": 228
  },
  {
    "full_name": "sisig-ai/doctor",
    "stargazers_count": 465,
    "open_issues_count": 9,
    "forks_count": 65
  },
  {
    "full_name": "felixmosh/bull-board",
    "stargazers_count": 3276,
    "open_issues_count": 26,
    "forks_count": 471
  },
  {
    "full_name": "Billionmail/BillionMail",
    "stargazers_count": 13968,
    "open_issues_count": 208,
    "forks_count": 1468
  },
  {
    "full_name": "Tech-Labi/medusa2-marketplace-demo",
    "stargazers_count": 76,
    "open_issues_count": 6,
    "forks_count": 22
  },
  {
    "full_name": "Nutlope/llamacoder",
    "stargazers_count": 6890,
    "open_issues_count": 9,
    "forks_count": 1641
  },
  {
    "full_name": "stack-auth/stack-auth",
    "stargazers_count": 6765,
    "open_issues_count": 38,
    "forks_count": 513
  },
  {
    "full_name": "DavidHDev/react-bits",
    "stargazers_count": 37998,
    "open_issues_count": 12,
    "forks_count": 1697
  },
  {
    "full_name": "valkey-io/valkey",
    "stargazers_count": 25450,
    "open_issues_count": 637,
    "forks_count": 1090
  },
  {
    "full_name": "puckeditor/puck",
    "stargazers_count": 12501,
    "open_issues_count": 190,
    "forks_count": 885
  },
  {
    "full_name": "invertase/notifee",
    "stargazers_count": 2181,
    "open_issues_count": 29,
    "forks_count": 275
  },
  {
    "full_name": "invertase/react-native-firebase",
    "stargazers_count": 12280,
    "open_issues_count": 96,
    "forks_count": 2324
  },
  {
    "full_name": "mui/base-ui",
    "stargazers_count": 9188,
    "open_issues_count": 360,
    "forks_count": 404
  },
  {
    "full_name": "nestjs/nest",
    "stargazers_count": 75175,
    "open_issues_count": 44,
    "forks_count": 8283
  },
  {
    "full_name": "andrewyng/aisuite",
    "stargazers_count": 13705,
    "open_issues_count": 128,
    "forks_count": 1444
  },
  {
    "full_name": "amruthpillai/reactive-resume",
    "stargazers_count": 36268,
    "open_issues_count": 63,
    "forks_count": 4020
  },
  {
    "full_name": "encoredev/encore",
    "stargazers_count": 11779,
    "open_issues_count": 103,
    "forks_count": 566
  },
  {
    "full_name": "The-Art-of-Hacking/h4cker",
    "stargazers_count": 25962,
    "open_issues_count": 0,
    "forks_count": 4942
  },
  {
    "full_name": "profilecity/vidur",
    "stargazers_count": 427,
    "open_issues_count": 36,
    "forks_count": 105
  },
  {
    "full_name": "dicedb/dicedb",
    "stargazers_count": 10729,
    "open_issues_count": 129,
    "forks_count": 1415
  },
  {
    "full_name": "sindresorhus/ora",
    "stargazers_count": 9660,
    "open_issues_count": 1,
    "forks_count": 286
  },
  {
    "full_name": "terkelg/prompts",
    "stargazers_count": 9263,
    "open_issues_count": 152,
    "forks_count": 320
  },
  {
    "full_name": "react-native-community/directory",
    "stargazers_count": 1361,
    "open_issues_count": 6,
    "forks_count": 807
  }
]