[
  {
    "full_name": "openstatusHQ/openstatus",
    "stargazers_count": 355,
    "open_issues_count": 22,
    "forks_count": 15
  },
  {
    "full_name": "Significant-Gravitas/Auto-GPT",
    "stargazers_count": 144120,
    "open_issues_count": 720,
    "forks_count": 31082
  },
  {
    "full_name": "emilkowalski/sonner",
    "stargazers_count": 3045,
    "open_issues_count": 0,
    "forks_count": 61
  },
  {
    "full_name": "master-co/css",
    "stargazers_count": 1546,
    "open_issues_count": 55,
    "forks_count": 39
  },
  {
    "full_name": "xitanggg/open-resume",
    "stargazers_count": 3290,
    "open_issues_count": 30,
    "forks_count": 210
  },
  {
    "full_name": "unkeyed/unkey",
    "stargazers_count": 698,
    "open_issues_count": 16,
    "forks_count": 33
  },
  {
    "full_name": "FlowiseAI/Flowise",
    "stargazers_count": 10721,
    "open_issues_count": 104,
    "forks_count": 3633
  },
  {
    "full_name": "react-page/react-page",
    "stargazers_count": 9220,
    "open_issues_count": 11,
    "forks_count": 651
  },
  {
    "full_name": "phosphor-icons/homepage",
    "stargazers_count": 2718,
    "open_issues_count": 110,
    "forks_count": 70
  },
  {
    "full_name": "prevwong/craft.js",
    "stargazers_count": 5969,
    "open_issues_count": 168,
    "forks_count": 606
  },
  {
    "full_name": "blocks/blocks",
    "stargazers_count": 4744,
    "open_issues_count": 66,
    "forks_count": 309
  },
  {
    "full_name": "webiny/webiny-js",
    "stargazers_count": 6674,
    "open_issues_count": 243,
    "forks_count": 538
  },
  {
    "full_name": "vercel/platforms",
    "stargazers_count": 3804,
    "open_issues_count": 9,
    "forks_count": 433
  },
  {
    "full_name": "vercel/static-fun",
    "stargazers_count": 559,
    "open_issues_count": 2,
    "forks_count": 62
  },
  {
    "full_name": "chapter-three/next-drupal",
    "stargazers_count": 428,
    "open_issues_count": 140,
    "forks_count": 134
  },
  {
    "full_name": "shadcn/ui",
    "stargazers_count": 24639,
    "open_issues_count": 480,
    "forks_count": 1158
  },
  {
    "full_name": "pacocoursey/cmdk",
    "stargazers_count": 6537,
    "open_issues_count": 41,
    "forks_count": 176
  },
  {
    "full_name": "calcom/cal.com",
    "stargazers_count": 21242,
    "open_issues_count": 655,
    "forks_count": 3306
  },
  {
    "full_name": "matteobruni/tsparticles",
    "stargazers_count": 5615,
    "open_issues_count": 21,
    "forks_count": 678
  },
  {
    "full_name": "react-pdf-viewer/react-pdf-viewer",
    "stargazers_count": 1662,
    "open_issues_count": 166,
    "forks_count": 157
  },
  {
    "full_name": "advanced-cropper/react-advanced-cropper",
    "stargazers_count": 382,
    "open_issues_count": 7,
    "forks_count": 19
  },
  {
    "full_name": "gilbarbara/react-joyride",
    "stargazers_count": 5763,
    "open_issues_count": 17,
    "forks_count": 485
  },
  {
    "full_name": "shuding/nextra",
    "stargazers_count": 8071,
    "open_issues_count": 223,
    "forks_count": 1004
  },
  {
    "full_name": "naptha/tesseract.js",
    "stargazers_count": 31028,
    "open_issues_count": 14,
    "forks_count": 2074
  },
  {
    "full_name": "microsoft/TaskMatrix",
    "stargazers_count": 33700,
    "open_issues_count": 227,
    "forks_count": 3262
  },
  {
    "full_name": "niklasvh/html2canvas",
    "stargazers_count": 28505,
    "open_issues_count": 923,
    "forks_count": 4691
  },
  {
    "full_name": "ajikan/ScribeAI",
    "stargazers_count": 120,
    "open_issues_count": 2,
    "forks_count": 16
  },
  {
    "full_name": "react-hook-form/react-hook-form",
    "stargazers_count": 35887,
    "open_issues_count": 16,
    "forks_count": 1805
  },
  {
    "full_name": "nextui-org/nextui",
    "stargazers_count": 11019,
    "open_issues_count": 160,
    "forks_count": 634
  },
  {
    "full_name": "nextui-org/tailwind-variants",
    "stargazers_count": 1071,
    "open_issues_count": 16,
    "forks_count": 23
  }
]