[
  {
    "full_name": "TryGhost/Ghost",
    "stargazers_count": 41034,
    "open_issues_count": 33,
    "forks_count": 8863
  },
  {
    "full_name": "gorhom/react-native-bottom-sheet",
    "stargazers_count": 3777,
    "open_issues_count": 66,
    "forks_count": 404
  },
  {
    "full_name": "remoteintech/remote-jobs",
    "stargazers_count": 19693,
    "open_issues_count": 35,
    "forks_count": 2155
  },
  {
    "full_name": "MohamedRadwan-DevOps/devops-step-by-step",
    "stargazers_count": 506,
    "open_issues_count": 7,
    "forks_count": 118
  },
  {
    "full_name": "alyssaxuu/omni",
    "stargazers_count": 5463,
    "open_issues_count": 39,
    "forks_count": 221
  },
  {
    "full_name": "alan2207/bulletproof-react",
    "stargazers_count": 14048,
    "open_issues_count": 22,
    "forks_count": 1130
  },
  {
    "full_name": "react-boilerplate/react-boilerplate-cra-template",
    "stargazers_count": 1576,
    "open_issues_count": 4,
    "forks_count": 325
  },
  {
    "full_name": "total-typescript/beginners-typescript-tutorial",
    "stargazers_count": 5225,
    "open_issues_count": 0,
    "forks_count": 476
  },
  {
    "full_name": "argyleink/open-props",
    "stargazers_count": 2475,
    "open_issues_count": 36,
    "forks_count": 107
  },
  {
    "full_name": "smartcontractkit/full-blockchain-solidity-course-js",
    "stargazers_count": 4997,
    "open_issues_count": 23,
    "forks_count": 1094
  },
  {
    "full_name": "fireship-io/flamethrower",
    "stargazers_count": 2359,
    "open_issues_count": 20,
    "forks_count": 97
  },
  {
    "full_name": "jollyjerr/react-autosave",
    "stargazers_count": 14,
    "open_issues_count": 2,
    "forks_count": 0
  },
  {
    "full_name": "novuhq/novu",
    "stargazers_count": 9234,
    "open_issues_count": 81,
    "forks_count": 456
  },
  {
    "full_name": "fonoster/fonoster",
    "stargazers_count": 5208,
    "open_issues_count": 25,
    "forks_count": 233
  },
  {
    "full_name": "primefaces/primereact",
    "stargazers_count": 3125,
    "open_issues_count": 200,
    "forks_count": 642
  },
  {
    "full_name": "EddieHubCommunity/LinkFree",
    "stargazers_count": 1056,
    "open_issues_count": 76,
    "forks_count": 978
  },
  {
    "full_name": "withfig/autocomplete",
    "stargazers_count": 19948,
    "open_issues_count": 183,
    "forks_count": 4665
  },
  {
    "full_name": "formkit/auto-animate",
    "stargazers_count": 5248,
    "open_issues_count": 36,
    "forks_count": 83
  },
  {
    "full_name": "themesberg/flowbite-react",
    "stargazers_count": 338,
    "open_issues_count": 67,
    "forks_count": 66
  },
  {
    "full_name": "giuseppeg/refined-twitter-lite",
    "stargazers_count": 101,
    "open_issues_count": 4,
    "forks_count": 5
  },
  {
    "full_name": "openreplay/openreplay",
    "stargazers_count": 5761,
    "open_issues_count": 57,
    "forks_count": 250
  },
  {
    "full_name": "oven-sh/bun",
    "stargazers_count": 33983,
    "open_issues_count": 390,
    "forks_count": 784
  },
  {
    "full_name": "gsoft-inc/sg-orbit",
    "stargazers_count": 91,
    "open_issues_count": 57,
    "forks_count": 33
  },
  {
    "full_name": "h5bp/Front-end-Developer-Interview-Questions",
    "stargazers_count": 55224,
    "open_issues_count": 6,
    "forks_count": 10640
  },
  {
    "full_name": "primer/react",
    "stargazers_count": 1923,
    "open_issues_count": 83,
    "forks_count": 321
  },
  {
    "full_name": "EddieHubCommunity/api",
    "stargazers_count": 53,
    "open_issues_count": 9,
    "forks_count": 54
  },
  {
    "full_name": "klaufel/awesome-design-systems",
    "stargazers_count": 472,
    "open_issues_count": 1,
    "forks_count": 38
  },
  {
    "full_name": "noob-hackers/infect",
    "stargazers_count": 1296,
    "open_issues_count": 5,
    "forks_count": 212
  },
  {
    "full_name": "WebDevSimplified/js-css-carousel",
    "stargazers_count": 38,
    "open_issues_count": 0,
    "forks_count": 30
  },
  {
    "full_name": "trananhtuat/switch-button-html-css-js",
    "stargazers_count": 8,
    "open_issues_count": 0,
    "forks_count": 2
  }
]